{
  "puzzles": [
    {
      "id": "Butterfly",
      "puzzleName": "Бабочка",
      "previewURL": "puzzles/Butterfly/preview.png",
      "difficulties": [
        { "pieceCount": 45, "piecesURL": "puzzles/Butterfly/easy/" },
        { "pieceCount": 77, "piecesURL": "puzzles/Butterfly/medium/" },
        { "pieceCount": 117, "piecesURL": "puzzles/Butterfly/hard/" }
      ]
    },
    {
      "id": "DevaA",
      "puzzleName": "Дева",
      "previewURL": "puzzles/DevaA/preview.png",
      "difficulties": [
        { "pieceCount": 45, "piecesURL": "puzzles/DevaA/easy/" },
        { "pieceCount": 77, "piecesURL": "puzzles/DevaA/medium/" },
        { "pieceCount": 117, "piecesURL": "puzzles/DevaA/hard/" }
      ]
    },
    {
      "id": "UkraI",
      "puzzleName": "Похищение звезды",
      "previewURL": "puzzles/UkraI/preview.png",
      "difficulties": [
        { "pieceCount": 45, "piecesURL": "puzzles/UkraI/easy/" },
        { "pieceCount": 77, "piecesURL": "puzzles/UkraI/medium/" },
        { "pieceCount": 117, "piecesURL": "puzzles/UkraI/hard/" }
      ]
    }
  ]
}